{
  "buildCommand" : {
    "command" : "build",
    "skipDependencies" : false,
    "style" : "buildAndRun"
  },
  "configuredTargets" : [
    {
      "guid" : "b4bd913b7e608a4e2f4f6200148f267efdbaeb47c2982e017608047960f67633"
    }
  ],
  "containerPath" : "/Users/dimas/CarshService/CarshService/build/Qt_6_8_0_for_iOS_ba71cd-Release/CarshService.xcodeproj",
  "continueBuildingAfterErrors" : false,
  "enableIndexBuildArena" : false,
  "hideShellScriptEnvironment" : false,
  "parameters" : {
    "action" : "build",
    "activeArchitecture" : "arm64",
    "activeRunDestination" : {
      "disableOnlyActiveArch" : false,
      "platform" : "iphoneos",
      "sdk" : "iphoneos17.2",
      "sdkVariant" : "iphoneos",
      "supportedArchitectures" : [
        "arm64v8",
        "arm64",
        "armv8"
      ],
      "targetArchitecture" : "arm64"
    },
    "arenaInfo" : {
      "buildIntermediatesPath" : "",
      "buildProductsPath" : "",
      "derivedDataPath" : "/Users/dimas/Library/Developer/Xcode/DerivedData",
      "indexDataStoreFolderPath" : "/Users/dimas/Library/Developer/Xcode/DerivedData/CarshService-ahsydsonuuqfudctkidmyhyamnep/Index.noindex/DataStore",
      "indexEnableDataStore" : true,
      "indexPCHPath" : "/Users/dimas/Library/Developer/Xcode/DerivedData/CarshService-ahsydsonuuqfudctkidmyhyamnep/Index.noindex/PrecompiledHeaders",
      "pchPath" : ""
    },
    "configurationName" : "Debug",
    "overrides" : {
      "synthesized" : {
        "table" : {
          "ASSETCATALOG_FILTER_FOR_DEVICE_MODEL" : "iPod9,1",
          "ASSETCATALOG_FILTER_FOR_DEVICE_OS_VERSION" : "15.8.3",
          "ASSETCATALOG_FILTER_FOR_THINNING_DEVICE_CONFIGURATION" : "iPod9,1",
          "BUILD_ACTIVE_RESOURCES_ONLY" : "YES",
          "ENABLE_PREVIEWS" : "NO",
          "ENABLE_XOJIT_PREVIEWS" : "NO",
          "TARGET_DEVICE_IDENTIFIER" : "e240e45c4af677efa3e36ab0a0fa7a1e2ebc8dc5",
          "TARGET_DEVICE_MODEL" : "iPod9,1",
          "TARGET_DEVICE_OS_VERSION" : "15.8.3",
          "TARGET_DEVICE_PLATFORM_NAME" : "iphoneos"
        }
      }
    }
  },
  "schemeCommand" : "launch",
  "showNonLoggedProgress" : true,
  "useDryRun" : false,
  "useImplicitDependencies" : true,
  "useLegacyBuildLocations" : false,
  "useParallelTargets" : true
}